toktokenizer-0.2.0.dist-info/METADATA
toktokenizer-0.2.0.dist-info/WHEEL
toktokenizer/__init__.py
toktokenizer/toktokenizer.cpython-311-aarch64-linux-gnu.so
toktokenizer-0.2.0.dist-info/RECORD
